__main__.py
ai_stream_proxy/__init__.py
ai_stream_proxy/client.py
ai_stream_proxy/stream.py
ai_stream_proxy-0.1.2.dist-info/METADATA
ai_stream_proxy-0.1.2.dist-info/WHEEL
ai_stream_proxy-0.1.2.dist-info/top_level.txt
ai_stream_proxy-0.1.2.dist-info/RECORD
