Metadata-Version: 2.4
Name: ai_stream_proxy
Version: 0.1.2
Summary: Client SDK for ai-stream-proxy.
Author-email: 有害猫猫拳 <637450802@qq.com>
Classifier: Programming Language :: Python :: 3
Classifier: License :: OSI Approved :: MIT License
Classifier: Operating System :: OS Independent
Requires-Python: <4.0,>=3.10
Requires-Dist: httpx
Requires-Dist: tenacity
